peb/__init__.py
peb/collections.py
peb/number.py
peb/regex.py
peb/text.py
peb/uri.py
peb/utils.py
peb-0.0.10.dist-info/LICENSE
peb-0.0.10.dist-info/METADATA
peb-0.0.10.dist-info/WHEEL
peb-0.0.10.dist-info/RECORD
